minesweeper/__init__.py
minesweeper/__main__.py
minesweeper/_text.py
minesweeper/cursor.py
minesweeper/game.py
minesweeper/play.py
minesweeper/read.py
minesweeper/version.py
ascii_minesweeper-1.0.1.dist-info/LICENSE
ascii_minesweeper-1.0.1.dist-info/METADATA
ascii_minesweeper-1.0.1.dist-info/WHEEL
ascii_minesweeper-1.0.1.dist-info/entry_points.txt
ascii_minesweeper-1.0.1.dist-info/top_level.txt
ascii_minesweeper-1.0.1.dist-info/RECORD
