Metadata-Version: 2.1
Name: ascii-minesweeper
Version: 1.0.1
Summary: An interactive minesweeper game for your terminal.
Home-page: https://github.com/nyoungstudios/ascii-minesweeper
Author: Nathaniel Young
Author-email: 
Maintainer: Nathaniel Young
Maintainer-email: 
License: MIT
Keywords: minesweeper ascii ascii-art terminal game python
Classifier: Environment :: Console
Classifier: Intended Audience :: Developers
Classifier: License :: OSI Approved :: MIT License
Classifier: Operating System :: OS Independent
Classifier: Programming Language :: Python :: 3
Classifier: Topic :: Games/Entertainment :: Puzzle Games
Classifier: Topic :: Terminals
License-File: LICENSE
Requires-Dist: numpy
